envanter/__init__.py
envanter/py.typed
envanter-1.3.0.dist-info/WHEEL
envanter-1.3.0.dist-info/METADATA
envanter-1.3.0.dist-info/RECORD
