Metadata-Version: 2.3
Name: envanter
Version: 1.3.0
Summary: Yet another environment parser.
Keywords: env,envparse,environment,environment-parser
Author: şuayip üzülmez
Author-email: şuayip üzülmez <suayip.541@gmail.com>
License: Copyright (c) 2022, Şuayip Üzülmez
Classifier: License :: OSI Approved :: BSD License
Classifier: Programming Language :: Python
Classifier: Programming Language :: Python :: 3
Classifier: Programming Language :: Python :: 3.10
Classifier: Programming Language :: Python :: 3.11
Classifier: Programming Language :: Python :: 3.12
Classifier: Programming Language :: Python :: 3.13
Requires-Python: >=3.10
Project-URL: Bug Tracker, https://github.com/realsuayip/envanter/issues
Project-URL: Homepage, https://github.com/realsuayip/envanter
